tweetpy/__init__.py
tweetpy/tweet.py
tweetpy-1.0.3.dist-info/LICENSE
tweetpy-1.0.3.dist-info/METADATA
tweetpy-1.0.3.dist-info/WHEEL
tweetpy-1.0.3.dist-info/top_level.txt
tweetpy-1.0.3.dist-info/RECORD
