Metadata-Version: 2.1
Name: tweetpy
Version: 1.0.3
Summary: Python package that allows to access the Tweet data without API
Home-page: https://tweetpy.elhellal.com/
Author: abdouhl
Author-email: <abderrahmane@elhellal.com>
License: MIT
Project-URL: Homepage, https://tweetpy.elhellal.com/
Project-URL: Source, https://github.com/abdouhl/tweetpy/
Project-URL: Documentation, https://tweetpy.elhellal.com#doc
Keywords: twitter,tweets,tweet,twitter_scraper,twitter_sentiment,status
License-File: LICENSE
